README.rst
setup.py
Origami.egg-info/PKG-INFO
Origami.egg-info/SOURCES.txt
Origami.egg-info/dependency_links.txt
Origami.egg-info/requires.txt
Origami.egg-info/top_level.txt
origami/__init__.py
origami/crafter.py
origami/test_origami.py
origami/util.py