Metadata-Version: 1.0
Name: Origami
Version: 0.3.0
Summary: Lightweight bit packing for classes
Home-page: https://github.com/numberoverzero/origami
Author: Joe Cross
Author-email: joe.mcross@gmail.com
License: LICENSE.txt
Platform: UNKNOWN
